chomp/__init__.py
chomp/chomp.py
chomp/config_manager.py
chomp/data_manager.py
chomp/food.py
chomp/utils.py
chomp/commands/__init__.py
chomp/commands/cook.py
chomp/commands/eat.py
chomp/commands/lookup_food.py
chomp/commands/measure.py
chomp/commands/search.py
chomp/commands/stats.py
chomp/commands/today.py
chomp/commands/weight.py
chompchomp-0.5.1.dist-info/METADATA
chompchomp-0.5.1.dist-info/WHEEL
chompchomp-0.5.1.dist-info/entry_points.txt
chompchomp-0.5.1.dist-info/licenses/LICENSE
chompchomp-0.5.1.dist-info/RECORD
